{
  "created_at": "Sat, 29 Sep 2012 13:58:44 +0000",
  "from_user": "zeroload",
  "from_user_id": 14908513,
  "from_user_id_str": "14908513",
  "from_user_name": "Vincent Voyer ",
  "geo": null,
  "id": 252044744954376200,
  "id_str": "252044744954376192",
  "iso_language_code": "en",
  "metadata": {
    "result_type": "recent"
  },
  "profile_image_url": "http://a0.twimg.com/profile_images/2286596117/ytzrxwusil1poelysdsx_normal.jpeg",
  "profile_image_url_https": "https://si0.twimg.com/profile_images/2286596117/ytzrxwusil1poelysdsx_normal.jpeg",
  "source": "&lt;a href=&quot;http://twitter.com/download/android&quot;&gt;Twitter for Android&lt;/a&gt;",
  "text": "RT @jsconf: RT @jsconf: Congrats to @dscape and team for what is clearly an awesome JS event in @lxjs Major props for organizing it!",
  "to_user": null,
  "to_user_id": 0,
  "to_user_id_str": "0",
  "to_user_name": null
}