{
  "created_at": "Sat, 29 Sep 2012 15:14:06 +0000",
  "from_user": "Jaydeep_W",
  "from_user_id": 471088692,
  "from_user_id_str": "471088692",
  "from_user_name": "Jaydeep",
  "geo": null,
  "id": 252063712201035780,
  "id_str": "252063712201035776",
  "iso_language_code": "en",
  "metadata": {
    "result_type": "recent"
  },
  "profile_image_url": "http://a0.twimg.com/profile_images/2441894377/jgozixtimhowb5qsawph_normal.jpeg",
  "profile_image_url_https": "https://si0.twimg.com/profile_images/2441894377/jgozixtimhowb5qsawph_normal.jpeg",
  "source": "&lt;a href=&quot;http://twitter.com/&quot;&gt;web&lt;/a&gt;",
  "text": "RT @JaneyLWang: RT @JaneyLWang: Jealous of the lucky folks in Portugal attending the Lisbon Javascript Conf. #node is all over it and such awesome modul ...",
  "to_user": null,
  "to_user_id": 0,
  "to_user_id_str": "0",
  "to_user_name": null
}