{
  "created_at": "Sat, 29 Sep 2012 14:35:25 +0000",
  "from_user": "hoaproject",
  "from_user_id": 59734282,
  "from_user_id_str": "59734282",
  "from_user_name": "Ivan Enderlin",
  "geo": null,
  "id": 252053976143519740,
  "id_str": "252053976143519744",
  "iso_language_code": "en",
  "metadata": {
    "result_type": "recent"
  },
  "profile_image_url": "http://a0.twimg.com/profile_images/796740034/twitterProfilePhoto_normal.jpg",
  "profile_image_url_https": "https://si0.twimg.com/profile_images/796740034/twitterProfilePhoto_normal.jpg",
  "source": "&lt;a href=&quot;http://twitter.com/download/iphone&quot;&gt;Twitter for iPhone&lt;/a&gt;",
  "text": "RT @janl: RT @janl: “Using frameworks is not a substitute for thinking.” — @karolinaszczur at @lxjs.",
  "to_user": null,
  "to_user_id": 0,
  "to_user_id_str": "0",
  "to_user_name": null
}