{
  "created_at": "Sat, 29 Sep 2012 20:16:30 +0000",
  "from_user": "NodeDublin",
  "from_user_id": 614155381,
  "from_user_id_str": "614155381",
  "from_user_name": "Node Dublin",
  "geo": null,
  "id": 252139813745094660,
  "id_str": "252139813745094656",
  "iso_language_code": "en",
  "metadata": {
    "result_type": "recent"
  },
  "profile_image_url": "http://a0.twimg.com/profile_images/2534633441/rqhd98wuzqcqxf8q97ov_normal.png",
  "profile_image_url_https": "https://si0.twimg.com/profile_images/2534633441/rqhd98wuzqcqxf8q97ov_normal.png",
  "source": "&lt;a href=&quot;http://itunes.apple.com/us/app/twitter/id409789998?mt=12&quot;&gt;Twitter for Mac&lt;/a&gt;",
  "text": "@dscape Lets do an lxjs discount for @NodeDublin",
  "to_user": "dscape",
  "to_user_id": 9279552,
  "to_user_id_str": "9279552",
  "to_user_name": "Nuno Job"
}