{
  "created_at": "Sun, 30 Sep 2012 02:04:47 +0000",
  "from_user": "mpelikan",
  "from_user_id": 131663,
  "from_user_id_str": "131663",
  "from_user_name": "Michael Pelikan",
  "geo": null,
  "id": 252227462656835600,
  "id_str": "252227462656835584",
  "iso_language_code": "en",
  "metadata": {
    "result_type": "recent"
  },
  "profile_image_url": "http://a0.twimg.com/profile_images/2662601729/514dbb2bcfb7b3635711ab6e7e6cadc3_normal.jpeg",
  "profile_image_url_https": "https://si0.twimg.com/profile_images/2662601729/514dbb2bcfb7b3635711ab6e7e6cadc3_normal.jpeg",
  "source": "&lt;a href=&quot;http://twitter.com/download/iphone&quot;&gt;Twitter for iPhone&lt;/a&gt;",
  "text": "RT @karolinaszczur: RT @karolinaszczur: Added some pictures to #lxjs Day One coverage - http://t.co/4rZbLwg6",
  "to_user": null,
  "to_user_id": 0,
  "to_user_id_str": "0",
  "to_user_name": null
}