{
  "created_at": "Sun, 30 Sep 2012 09:35:04 +0000",
  "from_user": "arif_iq",
  "from_user_id": 6592652,
  "from_user_id_str": "6592652",
  "from_user_name": "Mohammed Arif",
  "geo": null,
  "id": 252340777529790460,
  "id_str": "252340777529790464",
  "iso_language_code": "en",
  "metadata": {
    "result_type": "recent"
  },
  "profile_image_url": "http://a0.twimg.com/profile_images/370624680/mohammed_arif_normal.jpg",
  "profile_image_url_https": "https://si0.twimg.com/profile_images/370624680/mohammed_arif_normal.jpg",
  "source": "&lt;a href=&quot;http://www.flipboard.com&quot;&gt;Flipboard&lt;/a&gt;",
  "text": "RT @ialcazar: RT @ialcazar: Cnc.js: Building hardware with #Javascript #lxjs http://t.co/HbtBH6oN",
  "to_user": null,
  "to_user_id": 0,
  "to_user_id_str": "0",
  "to_user_name": null
}