{
  "created_at": "Sun, 30 Sep 2012 14:39:48 +0000",
  "from_user": "ralphtheninja",
  "from_user_id": 39033726,
  "from_user_id_str": "39033726",
  "from_user_name": "Lars Magnus Skog",
  "geo": null,
  "id": 252417466871996400,
  "id_str": "252417466871996416",
  "iso_language_code": "en",
  "metadata": {
    "result_type": "recent"
  },
  "profile_image_url": "http://a0.twimg.com/profile_images/2453119926/g7aqkk2hr8ahta7p1tnm_normal.jpeg",
  "profile_image_url_https": "https://si0.twimg.com/profile_images/2453119926/g7aqkk2hr8ahta7p1tnm_normal.jpeg",
  "source": "&lt;a href=&quot;http://twitter.com/&quot;&gt;web&lt;/a&gt;",
  "text": "Last night was awesome. I had a great time! Home at 6AM and hungover like a motherfucker :) #lxjs",
  "to_user": null,
  "to_user_id": 0,
  "to_user_id_str": "0",
  "to_user_name": null
}